bssl_integrations/__init__.py
bssl_integrations/aiohttp.py
bssl_integrations/aiohttp_socks.py
bssl_integrations/httpx/__init__.py
bssl_integrations/httpx/proxy.py
bssl_integrations/httpx/sync.py
bssl_integrations/ssl.py
bssl_integrations-1.0.0a0.dist-info/WHEEL
bssl_integrations-1.0.0a0.dist-info/METADATA
bssl_integrations-1.0.0a0.dist-info/RECORD
