Metadata-Version: 2.4
Name: bssl-integrations
Version: 1.0.0a0
Summary: BSSL project integration with existing http clients
Keywords: bssl,boringssl,tls,http,aiohttp,httpx
Author: Dmytro Tkachenko
Author-email: Dmytro Tkachenko <itsme@somespecial.one>
License-Expression: MIT
Classifier: Programming Language :: Python
Classifier: Typing :: Typed
Classifier: Intended Audience :: Developers
Classifier: Intended Audience :: Information Technology
Classifier: Topic :: Software Development
Classifier: Topic :: Software Development :: Libraries
Classifier: Topic :: Software Development :: Libraries :: Python Modules
Classifier: Programming Language :: Python :: 3
Classifier: Programming Language :: Python :: 3 :: Only
Classifier: Programming Language :: Python :: 3.12
Classifier: Programming Language :: Python :: 3.13
Classifier: Programming Language :: Python :: 3.14
Classifier: Operating System :: Microsoft :: Windows
Classifier: Operating System :: POSIX
Classifier: Operating System :: Unix
Classifier: Operating System :: MacOS
Classifier: Development Status :: 3 - Alpha
Requires-Dist: bssl>=1.0.0a0
Requires-Python: >=3.12
Project-URL: Bug Tracker, https://github.com/somespecialone/bssl-integrations/issues
Project-URL: Documentation, https://github.com/somespecialone/bssl-integrations
Project-URL: Homepage, https://github.com/somespecialone/bssl-integrations
Project-URL: Repository, https://github.com/somespecialone/bssl-integrations/
